aiohttp_sentry/__init__.py
aiohttp_sentry-0.6.0.dist-info/LICENSE
aiohttp_sentry-0.6.0.dist-info/METADATA
aiohttp_sentry-0.6.0.dist-info/WHEEL
aiohttp_sentry-0.6.0.dist-info/top_level.txt
aiohttp_sentry-0.6.0.dist-info/RECORD
