Metadata-Version: 2.1
Name: aiohttp-sentry
Version: 0.6.0
Summary: An aiohttp middleware for reporting errors to Sentry
Home-page: https://github.com/underyx/aiohttp-sentry
Author: Bence Nagy
Author-email: bence@underyx.me
Maintainer: Bence Nagy
Maintainer-email: bence@underyx.me
License: UNKNOWN
Download-URL: https://github.com/underyx/aiohttp-sentry/releases
Platform: UNKNOWN
Classifier: Development Status :: 4 - Beta
Classifier: License :: OSI Approved :: MIT License
Classifier: Operating System :: OS Independent
Classifier: Programming Language :: Python :: 3 :: Only
Classifier: Programming Language :: Python :: 3.7
Requires-Dist: raven-aiohttp (~=0.7.0)
Requires-Dist: raven (~=6.10)
